ctx.py
util.py
ccc/__init__.py
ccc/alicloud.py
ccc/aws.py
ccc/cfg.py
ccc/clamav.py
ccc/concourse.py
ccc/delivery.py
ccc/elasticsearch.py
ccc/gcp.py
ccc/github.py
ccc/grafeas_model.py
ccc/oci.py
ccc/protecode.py
ccc/secrets_server.py
ccc/slack.py
ci/__init__.py
ci/log.py
ci/paths.py
ci/util.py
model/__init__.py
model/alicloud.py
model/aws.py
model/azure.py
model/base.py
model/btp_application_certificate.py
model/btp_service_binding.py
model/ccee.py
model/checkmarx.py
model/clamav.py
model/concourse.py
model/config_repo.py
model/container_registry.py
model/ctx_repository.py
model/delivery.py
model/delivery_db.py
model/docker.py
model/elasticsearch.py
model/email.py
model/gardenlinux_cache.py
model/gcp.py
model/github.py
model/gitlab.py
model/ingress.py
model/jira.py
model/kubernetes.py
model/oauth2_proxy.py
model/protecode.py
model/proxy.py
model/pypi.py
model/secret.py
model/secrets_server.py
model/signing_server.py
model/slack.py
model/tekton.py
model/tekton_dashboard_ingress.py
model/victorops.py
model/webhook_dispatcher.py
oci/__init__.py
oci/auth.py
oci/client.py
oci/convert.py
oci/docker.py
oci/kaniko.py
oci/model.py
oci/platform.py
oci/util.py
oci/workarounds.py
gardener_cicd_base-1.2459.0.dist-info/LICENSE
gardener_cicd_base-1.2459.0.dist-info/METADATA
gardener_cicd_base-1.2459.0.dist-info/WHEEL
gardener_cicd_base-1.2459.0.dist-info/top_level.txt
gardener_cicd_base-1.2459.0.dist-info/RECORD
