Metadata-Version: 2.1
Name: gardener-cicd-base
Version: 1.2459.0
Summary: Gardener CI/CD Base Libraries
Requires-Python: >=3.11
License-File: LICENSE
Requires-Dist: elasticsearch<8.0.0,>=7.13
Requires-Dist: pyyaml
Requires-Dist: ruamel.yaml==0.17.21
Requires-Dist: termcolor
Requires-Dist: urllib3
Requires-Dist: yamllint
